odoo10_addon_l10n_it_ricevute_bancarie-10.0.1.0.3-py2.7-nspkg.pth
odoo/addons/l10n_it_ricevute_bancarie/README.rst
odoo/addons/l10n_it_ricevute_bancarie/__init__.py
odoo/addons/l10n_it_ricevute_bancarie/__manifest__.py
odoo/addons/l10n_it_ricevute_bancarie/report.xml
odoo/addons/l10n_it_ricevute_bancarie/riba_sequence.xml
odoo/addons/l10n_it_ricevute_bancarie/riba_workflow.xml
odoo/addons/l10n_it_ricevute_bancarie/demo/riba_demo.xml
odoo/addons/l10n_it_ricevute_bancarie/i18n/am.po
odoo/addons/l10n_it_ricevute_bancarie/i18n/ar.po
odoo/addons/l10n_it_ricevute_bancarie/i18n/bg.po
odoo/addons/l10n_it_ricevute_bancarie/i18n/bs.po
odoo/addons/l10n_it_ricevute_bancarie/i18n/ca.po
odoo/addons/l10n_it_ricevute_bancarie/i18n/ca_ES.po
odoo/addons/l10n_it_ricevute_bancarie/i18n/cs.po
odoo/addons/l10n_it_ricevute_bancarie/i18n/da.po
odoo/addons/l10n_it_ricevute_bancarie/i18n/de.po
odoo/addons/l10n_it_ricevute_bancarie/i18n/el_GR.po
odoo/addons/l10n_it_ricevute_bancarie/i18n/en_AU.po
odoo/addons/l10n_it_ricevute_bancarie/i18n/en_GB.po
odoo/addons/l10n_it_ricevute_bancarie/i18n/es.po
odoo/addons/l10n_it_ricevute_bancarie/i18n/es_AR.po
odoo/addons/l10n_it_ricevute_bancarie/i18n/es_CL.po
odoo/addons/l10n_it_ricevute_bancarie/i18n/es_CO.po
odoo/addons/l10n_it_ricevute_bancarie/i18n/es_CR.po
odoo/addons/l10n_it_ricevute_bancarie/i18n/es_DO.po
odoo/addons/l10n_it_ricevute_bancarie/i18n/es_EC.po
odoo/addons/l10n_it_ricevute_bancarie/i18n/es_ES.po
odoo/addons/l10n_it_ricevute_bancarie/i18n/es_MX.po
odoo/addons/l10n_it_ricevute_bancarie/i18n/es_PE.po
odoo/addons/l10n_it_ricevute_bancarie/i18n/es_PY.po
odoo/addons/l10n_it_ricevute_bancarie/i18n/es_VE.po
odoo/addons/l10n_it_ricevute_bancarie/i18n/et.po
odoo/addons/l10n_it_ricevute_bancarie/i18n/eu.po
odoo/addons/l10n_it_ricevute_bancarie/i18n/fa.po
odoo/addons/l10n_it_ricevute_bancarie/i18n/fi.po
odoo/addons/l10n_it_ricevute_bancarie/i18n/fr.po
odoo/addons/l10n_it_ricevute_bancarie/i18n/fr_CA.po
odoo10_addon_l10n_it_ricevute_bancarie-10.0.1.0.3.dist-info/DESCRIPTION.rst
odoo10_addon_l10n_it_ricevute_bancarie-10.0.1.0.3.dist-info/METADATA
odoo10_addon_l10n_it_ricevute_bancarie-10.0.1.0.3.dist-info/RECORD
odoo10_addon_l10n_it_ricevute_bancarie-10.0.1.0.3.dist-info/WHEEL
odoo10_addon_l10n_it_ricevute_bancarie-10.0.1.0.3.dist-info/metadata.json
odoo10_addon_l10n_it_ricevute_bancarie-10.0.1.0.3.dist-info/namespace_packages.txt
odoo10_addon_l10n_it_ricevute_bancarie-10.0.1.0.3.dist-info/top_level.txt
